taggy/__init__.py
taggy/cli.py
taggy/prompts.py
taggy/semver.py
taggy-0.3.0.dist-info/DESCRIPTION.rst
taggy-0.3.0.dist-info/METADATA
taggy-0.3.0.dist-info/RECORD
taggy-0.3.0.dist-info/WHEEL
taggy-0.3.0.dist-info/entry_points.txt
taggy-0.3.0.dist-info/metadata.json
taggy-0.3.0.dist-info/top_level.txt
